example/BasicTest.py
example/__init__.py
example/example.py
tgasdk/__init__.py
tgasdk/sdk.py
ThinkingDataSdk-3.0.0.dist-info/LICENSE.txt
ThinkingDataSdk-3.0.0.dist-info/METADATA
ThinkingDataSdk-3.0.0.dist-info/WHEEL
ThinkingDataSdk-3.0.0.dist-info/top_level.txt
ThinkingDataSdk-3.0.0.dist-info/RECORD
