Metadata-Version: 2.1
Name: ThinkingDataSdk
Version: 3.0.0
Summary: Official ThinkingData Analytics library for Python
Home-page: https://github.com/ThinkingDataAnalytics/python-sdk
Author: ThinkingData, Inc.
Author-email: sdk@thinkingdata.cn
License: Apache
Platform: all
Classifier: License :: OSI Approved :: Apache Software License
Classifier: Operating System :: OS Independent
Classifier: Intended Audience :: Developers
Classifier: Programming Language :: Python :: 2
Classifier: Programming Language :: Python :: 3
Classifier: Topic :: Software Development :: Libraries
License-File: LICENSE.txt
Requires-Dist: requests
